xmanual/__init__.py
xmanual/utils/__init__.py
xmanual/utils/attribute.py
xmanual/utils/man.py
xmanual-0.5.dist-info/LICENSE
xmanual-0.5.dist-info/METADATA
xmanual-0.5.dist-info/WHEEL
xmanual-0.5.dist-info/top_level.txt
xmanual-0.5.dist-info/zip-safe
xmanual-0.5.dist-info/RECORD
